mistral_ocr/__init__.py
mistral_ocr/image.py
mistral_ocr/parser.py
mistral_ocr/utils.py
mistral_ocr_parser-0.1.0.dist-info/LICENSE
mistral_ocr_parser-0.1.0.dist-info/METADATA
mistral_ocr_parser-0.1.0.dist-info/WHEEL
mistral_ocr_parser-0.1.0.dist-info/entry_points.txt
mistral_ocr_parser-0.1.0.dist-info/top_level.txt
mistral_ocr_parser-0.1.0.dist-info/RECORD
