Metadata-Version: 2.2
Name: mistral-ocr-parser
Version: 0.1.0
Summary: A library for parsing PDF documents using Mistral's OCR API
Author-email: Ravi Raina <raviraina17@gmail.com>
License: MIT
Project-URL: Homepage, https://github.com/raviraina/mistral-ocr-parser
Project-URL: Bug Tracker, https://github.com/raviraina/mistral-ocr-parser/issues
Classifier: Programming Language :: Python :: 3
Classifier: Programming Language :: Python :: 3.9
Classifier: Programming Language :: Python :: 3.10
Classifier: Programming Language :: Python :: 3.11
Classifier: Programming Language :: Python :: 3.12
Classifier: License :: OSI Approved :: MIT License
Classifier: Operating System :: OS Independent
Requires-Python: >=3.9
License-File: LICENSE
Requires-Dist: mistralai>=0.0.10
Requires-Dist: python-dotenv>=1.0.0
Requires-Dist: markdown>=3.5.1
Requires-Dist: pillow>=10.0.0
Requires-Dist: tqdm>=4.66.1
Requires-Dist: pycountry>=22.3.5
Provides-Extra: dev
Requires-Dist: pytest>=7.0.0; extra == "dev"
Requires-Dist: pytest-cov>=4.0.0; extra == "dev"
Requires-Dist: black>=23.0.0; extra == "dev"
Requires-Dist: isort>=5.12.0; extra == "dev"
Requires-Dist: flake8>=6.0.0; extra == "dev"
Requires-Dist: mypy>=1.0.0; extra == "dev"
